{
  "id": "tutorials/custom-scenarios",
  "title": "Custom Scenarios",
  "description": "Learn how to create and configure custom federated learning scenarios to test different network conditions, client behaviors, and system configurations.",
  "source": "@site/docs/tutorials/custom-scenarios.md",
  "sourceDirName": "tutorials",
  "slug": "/tutorials/custom-scenarios",
  "permalink": "/flopy-net/docs/tutorials/custom-scenarios",
  "draft": false,
  "unlisted": false,
  "editUrl": "https://github.com/abdulmelink/flopy-net/tree/main/docs/docs/tutorials/custom-scenarios.md",
  "tags": [],
  "version": "current",
  "sidebarPosition": 2,
  "frontMatter": {
    "sidebar_position": 2
  },
  "sidebar": "tutorialSidebar",
  "previous": {
    "title": "Basic Federated Learning Experiment",
    "permalink": "/flopy-net/docs/tutorials/basic-experiment"
  },
  "next": {
    "title": "Advanced Configuration",
    "permalink": "/flopy-net/docs/tutorials/advanced-configuration"
  }
}